odoo/addons/account_tax_one_vat_sale/README.rst
odoo/addons/account_tax_one_vat_sale/__init__.py
odoo/addons/account_tax_one_vat_sale/__manifest__.py
odoo/addons/account_tax_one_vat_sale/i18n/account_tax_one_vat_sale.pot
odoo/addons/account_tax_one_vat_sale/i18n/it.po
odoo/addons/account_tax_one_vat_sale/models/__init__.py
odoo/addons/account_tax_one_vat_sale/models/sale_order_line.py
odoo/addons/account_tax_one_vat_sale/readme/CONTRIBUTORS.rst
odoo/addons/account_tax_one_vat_sale/readme/DESCRIPTION.rst
odoo/addons/account_tax_one_vat_sale/static/description/icon.png
odoo/addons/account_tax_one_vat_sale/static/description/index.html
odoo/addons/account_tax_one_vat_sale/tests/__init__.py
odoo/addons/account_tax_one_vat_sale/tests/test_account_tax_one_vat_sale.py
odoo_addon_account_tax_one_vat_sale-16.0.1.0.0.5.dist-info/METADATA
odoo_addon_account_tax_one_vat_sale-16.0.1.0.0.5.dist-info/WHEEL
odoo_addon_account_tax_one_vat_sale-16.0.1.0.0.5.dist-info/top_level.txt
odoo_addon_account_tax_one_vat_sale-16.0.1.0.0.5.dist-info/RECORD
